blobtoolkit-host/setup.py
blobtoolkit-host/src/__init__.py
blobtoolkit-host/src/__main__.py
blobtoolkit-host/src/blobtoolkit_host.py
blobtoolkit-host/src/lib/__init__.py
blobtoolkit-host/src/lib/host.py
blobtoolkit-host/src/lib/version.py
blobtoolkit-pipeline/setup.py
blobtoolkit-pipeline/src/__init__.py
blobtoolkit-pipeline/src/blobtoolkit_pipeline.py
blobtoolkit-pipeline/src/lib/__init__.py
blobtoolkit-pipeline/src/lib/add_summary_to_metadata.py
blobtoolkit-pipeline/src/lib/chunk_fasta.py
blobtoolkit-pipeline/src/lib/count_busco_genes.py
blobtoolkit-pipeline/src/lib/data.py
blobtoolkit-pipeline/src/lib/extract_busco_genes.py
blobtoolkit-pipeline/src/lib/functions.py
blobtoolkit-pipeline/src/lib/generate_config.py
blobtoolkit-pipeline/src/lib/generate_static_images.py
blobtoolkit-pipeline/src/lib/resume_pipeline.py
blobtoolkit-pipeline/src/lib/run.py
blobtoolkit-pipeline/src/lib/track_bioproject_accessions.py
blobtoolkit-pipeline/src/lib/transfer_completed.py
blobtoolkit-pipeline/src/lib/unchunk_blast.py
blobtoolkit-pipeline/src/lib/version.py
blobtoolkit-pipeline/src/lib/window_stats.py
blobtools/__init__.py
blobtools/__main__.py
blobtools/blobtools.py
blobtools/lib/__init__.py
blobtools/lib/add.py
blobtools/lib/bed.py
blobtools/lib/blob_db.py
blobtools/lib/busco.py
blobtools/lib/calc.py
blobtools/lib/cov.py
blobtools/lib/dataset.py
blobtools/lib/fasta.py
blobtools/lib/fetch.py
blobtools/lib/field.py
blobtools/lib/file_io.py
blobtools/lib/filter.py
blobtools/lib/hits.py
blobtools/lib/host.py
blobtools/lib/key.py
blobtools/lib/link.py
blobtools/lib/remove.py
blobtools/lib/synonyms.py
blobtools/lib/taxdump.py
blobtools/lib/taxid.py
blobtools/lib/text.py
blobtools/lib/trnascan.py
blobtools/lib/validate.py
blobtools/lib/version.py
blobtools/lib/view.py
btk/__init__.py
btk/__main__.py
btk/btk.py
btk/lib/pipeline.py
btk/lib/version.py
data/setup.py
data/schema/basic.schema.json
data/schema/meta.schema.json
data/schema/subschemas/array.data.schema.json
blobtoolkit-4.5.0.dist-info/AUTHORS
blobtoolkit-4.5.0.dist-info/LICENSE
blobtoolkit-4.5.0.dist-info/METADATA
blobtoolkit-4.5.0.dist-info/WHEEL
blobtoolkit-4.5.0.dist-info/entry_points.txt
blobtoolkit-4.5.0.dist-info/top_level.txt
blobtoolkit-4.5.0.dist-info/RECORD
