Metadata-Version: 2.1
Name: blobtoolkit
Version: 4.5.0
Summary: blobtoolkit
Home-page: https://github.com/blobtoolkit/blobtoolkit
Author: blobtoolkit
Author-email: blobtoolkit@genomehubs.org
Project-URL: Bug Reports, https://github.com/blobtoolkit/blobtoolkit/issues
Project-URL: Source, https://github.com/blobtoolkit/blobtoolkit
Keywords: bioinformatics
Classifier: Development Status :: 5 - Production/Stable
Classifier: Intended Audience :: Science/Research
Classifier: Topic :: Scientific/Engineering :: Bio-Informatics
Classifier: License :: OSI Approved :: MIT License
Classifier: Programming Language :: Python :: 3
Classifier: Programming Language :: Python :: 3.9
Classifier: Programming Language :: Python :: 3.10
Classifier: Programming Language :: Python :: 3.11
Classifier: Programming Language :: Python :: 3.12
Classifier: Programming Language :: Python :: 3.13
Classifier: Programming Language :: Python :: 3 :: Only
Requires-Python: >=3.9, <3.14
License-File: LICENSE
License-File: AUTHORS
Requires-Dist: blobtk>=0.7.9
Requires-Dist: chromedriver-autoinstaller>=0.6.2
Requires-Dist: docopt>=0.6.2
Requires-Dist: fastjsonschema>=2.21.1
Requires-Dist: geckodriver-autoinstaller>=0.1.0
Requires-Dist: psutil==5.9.4
Requires-Dist: pyvirtualdisplay==3.0
Requires-Dist: pyyaml
Requires-Dist: selenium>=4.10.0
Requires-Dist: tolkein>=0.5.0
Requires-Dist: tqdm==4.64.1
Requires-Dist: ujson>=5.7.0
Provides-Extra: dev
Requires-Dist: pycodestyle>=2.6.0; extra == "dev"
Requires-Dist: pydocstyle>=5.0.2; extra == "dev"
Requires-Dist: pylint>=2.5.3; extra == "dev"
Provides-Extra: full
Requires-Dist: blobtoolkit-host==4.5.0; extra == "full"
Requires-Dist: blobtoolkit-pipeline==4.4.6; extra == "full"
Provides-Extra: host
Requires-Dist: blobtoolkit-host==4.5.0; extra == "host"
Provides-Extra: pipeline
Requires-Dist: blobtoolkit-pipeline==4.4.6; extra == "pipeline"
Provides-Extra: test
Requires-Dist: coverage>=5.1; extra == "test"
Requires-Dist: coveralls>=2.0.0; extra == "test"
Requires-Dist: mock>=4.0.2; extra == "test"
Requires-Dist: pytest-cov>=2.10.0; extra == "test"
Requires-Dist: pytest-isort>=5; extra == "test"
Requires-Dist: pytest-mock>=3.1.1; extra == "test"
Requires-Dist: pytest>=6.0.0; extra == "test"
